asynctwitch/__init__.py
asynctwitch/bots.py
asynctwitch/dataclasses.py
asynctwitch-4.2.1.dist-info/DESCRIPTION.rst
asynctwitch-4.2.1.dist-info/METADATA
asynctwitch-4.2.1.dist-info/RECORD
asynctwitch-4.2.1.dist-info/WHEEL
asynctwitch-4.2.1.dist-info/metadata.json
asynctwitch-4.2.1.dist-info/top_level.txt
