Metadata-Version: 2.0
Name: asynctwitch
Version: 4.2.1
Summary: Asynchonous wrapper for twitch IRC3
Home-page: https://github.com/martmists/asynctwitch
Author: martmists
Author-email: martmists@gmail.com
License: BSD-3-Clause
Keywords: asyncio twitch irc
Platform: UNKNOWN
Classifier: Development Status :: 5 - Production/Stable
Classifier: Intended Audience :: Developers
Classifier: Topic :: Communications :: Chat
Classifier: License :: OSI Approved :: BSD License
Classifier: Programming Language :: Python :: 3.4
Requires-Dist: aiohttp
Requires-Dist: isodate
